[
  {
    "id": 40001,
    "priority": 1,
    "action": {
      "type": "block"
    },
    "condition": {
      "urlFilter": "*://googleads.g.doubleclick.net/*",
      "resourceTypes": [
        "script",
        "xmlhttprequest",
        "image",
        "sub_frame"
      ]
    }
  },
  {
    "id": 40002,
    "priority": 1,
    "action": {
      "type": "block"
    },
    "condition": {
      "urlFilter": "*://tpc.googlesyndication.com/*",
      "resourceTypes": [
        "script",
        "xmlhttprequest",
        "image"
      ]
    }
  },
  {
    "id": 40003,
    "priority": 1,
    "action": {
      "type": "block"
    },
    "condition": {
      "urlFilter": "*://youtube.com/pagead/*",
      "resourceTypes": [
        "script",
        "xmlhttprequest",
        "image",
        "sub_frame"
      ]
    }
  },
  {
    "id": 40004,
    "priority": 1,
    "action": {
      "type": "block"
    },
    "condition": {
      "urlFilter": "*://www.youtube.com/api/stats/ads*",
      "resourceTypes": [
        "xmlhttprequest"
      ]
    }
  },
  {
    "id": 40005,
    "priority": 1,
    "action": {
      "type": "block"
    },
    "condition": {
      "urlFilter": "*://s.youtube.com/api/stats/watchtime*",
      "resourceTypes": [
        "xmlhttprequest"
      ]
    }
  }
]